MANIFEST.in
pyrx.py
readme.md
setup.py
pyrx_ats.egg-info/PKG-INFO
pyrx_ats.egg-info/SOURCES.txt
pyrx_ats.egg-info/dependency_links.txt
pyrx_ats.egg-info/top_level.txt
test/test_pyrx.py