Metadata-Version: 1.0
Name: pyrx-ats
Version: 0.3.1
Summary: Rx schema and validation system, with added error messages
Home-page: https://github.com/advancedtelematic/pyrx
Author: UNKNOWN
Author-email: UNKNOWN
License: GPLv2
Platform: UNKNOWN
